check_your_heuristic/Base.py
check_your_heuristic/__init__.py
check_your_heuristic/configs.py
check_your_heuristic/main.py
check_your_heuristic/utils.py
check_your_heuristic/dataset/BaseDataset.py
check_your_heuristic/dataset/Dataset.py
check_your_heuristic/dataset/MultiRCDataset.py
check_your_heuristic/dataset/ReCoRDDataset.py
check_your_heuristic/dataset/__init__.py
check_your_heuristic/heuristics/BasicHeuristics.py
check_your_heuristic/heuristics/Heuristic.py
check_your_heuristic/heuristics/ReCoRDHeuristics.py
check_your_heuristic/heuristics/WordInContextHeuristics.py
check_your_heuristic/heuristics/__init__.py
tests/__init__.py
tests/test_BaseSolver.py
check_your_heuristic-0.0.2.dist-info/LICENSE.txt
check_your_heuristic-0.0.2.dist-info/METADATA
check_your_heuristic-0.0.2.dist-info/WHEEL
check_your_heuristic-0.0.2.dist-info/entry_points.txt
check_your_heuristic-0.0.2.dist-info/top_level.txt
check_your_heuristic-0.0.2.dist-info/RECORD
