Metadata-Version: 2.1
Name: check-your-heuristic
Version: 0.0.2
Summary: Small library which aim is to check your dataset for being solved by simple heuristics. Multilingual!
Author: Tatiana Iazykova, Olga Bystrova, Denis Kapelyushnik
Author-email: tania_yazykova@bk.ru
License: MIT
Keywords: heuristics,rule-based,language models,natural language understanding,nlp
Platform: UNKNOWN
Classifier: Development Status :: 3 - Alpha
Classifier: Intended Audience :: Developers
Classifier: Topic :: Software Development :: Build Tools
Classifier: License :: OSI Approved :: MIT License
Classifier: Programming Language :: Python :: 3.7
Classifier: Programming Language :: Python :: 3.8
Classifier: Programming Language :: Python :: 3.9
License-File: LICENSE.txt
Requires-Dist: numpy (>=1.19.0)
Requires-Dist: pandas (>=1.1.5)
Requires-Dist: scikit-learn (>=0.24.2)
Requires-Dist: pymorphy2 (>=0.9.1)
Requires-Dist: pyyaml
Requires-Dist: nptyping (>=1.4.4)
Requires-Dist: parameterized (>=0.8.1)
Requires-Dist: openpyxl (>=3.0.9)
Requires-Dist: matplotlib (>=3.4.3)
Requires-Dist: seaborn (>=0.11.0)
